easyscript/__init__.py
easyscript/__main__.py
easyscript/easyscript.py
easyscript/repl.py
easyscript-0.6.6.dist-info/licenses/LICENSE
easyscript-0.6.6.dist-info/METADATA
easyscript-0.6.6.dist-info/WHEEL
easyscript-0.6.6.dist-info/entry_points.txt
easyscript-0.6.6.dist-info/top_level.txt
easyscript-0.6.6.dist-info/RECORD
