Metadata-Version: 2.4
Name: easyscript
Version: 0.6.6
Summary: A simple scripting language that blends Python and JavaScript syntax
Author-email: EasyScript <java4life@gmail.com>
License-Expression: MIT
Project-URL: Homepage, https://github.com/rhulha/easyscript
Project-URL: Documentation, https://github.com/rhulha/easyscript#readme
Project-URL: Repository, https://github.com/rhulha/easyscript
Project-URL: Bug Reports, https://github.com/rhulha/easyscript/issues
Keywords: scripting,language,interpreter,javascript,python,regex
Classifier: Development Status :: 4 - Beta
Classifier: Intended Audience :: Developers
Classifier: Operating System :: OS Independent
Classifier: Programming Language :: Python :: 3
Classifier: Programming Language :: Python :: 3.7
Classifier: Programming Language :: Python :: 3.8
Classifier: Programming Language :: Python :: 3.9
Classifier: Programming Language :: Python :: 3.10
Classifier: Programming Language :: Python :: 3.11
Classifier: Programming Language :: Python :: 3.12
Classifier: Topic :: Software Development :: Interpreters
Classifier: Topic :: Software Development :: Libraries :: Python Modules
Requires-Python: >=3.7
License-File: LICENSE
Provides-Extra: dev
Requires-Dist: pytest>=6.0; extra == "dev"
Requires-Dist: black; extra == "dev"
Requires-Dist: flake8; extra == "dev"
Dynamic: license-file
